{
  "businessName": "Solutions In Motion",
  "tagline": "Robotic Lawn Mower Consulting, Setup & Support",
  "about": "Solutions In Motion provides professional consulting, installation, optimization, and ongoing support for robotic lawn mowers. We help homeowners automate their lawn care with reliable, high‑performance robotic mowing systems.",
  "services": {
    "consulting_selection": {
      "title": "Consulting & Selection",
      "description": "We evaluate your property and recommend the best robotic mower based on performance, reliability, yard layout, and budget."
    },
    "professional_installation": {
      "title": "Professional Installation",
      "description": "Complete installation including boundary wire layout, charging station placement, zoning, and full system testing."
    },
    "troubleshooting_repairs": {
      "title": "Troubleshooting & Repairs",
      "description": "Fix navigation errors, boundary issues, docking problems, poor coverage, and other mower performance issues."
    },
    "efficiency_optimization": {
      "title": "Efficiency Optimization",
      "description": "Schedule tuning, cutting pattern adjustments, zone refinement, and seasonal optimization for maximum performance."
    }
  },
  "supportedBrands": {
    "ecovacs_goat": {
      "title": "Ecovacs GOAT",
      "description": "Advanced RTK and vision‑based configuration, multi‑zone tuning, and firmware optimization."
    },
    "worx_landroid": {
      "title": "Worx Landroid",
      "description": "Boundary wire optimization, ACS setup, zone management, and slope tuning."
    },
    "all_brands": {
      "title": "All Brands Supported",
      "description": "Support for any robotic mower brand including Husqvarna, Segway, Gardena, and more."
    }
  },
  "pricing": {
    "consultation": {
      "title": "Consultation",
      "price": "$99",
      "details": "On‑site or virtual assessment.",
      "depositLink": "#stripe"
    },
    "installation": {
      "title": "Installation",
      "price": "Starting at $399",
      "details": "Price varies based on yard size.",
      "depositLink": "#stripe"
    },
    "optimization_visit": {
      "title": "Optimization Visit",
      "price": "$149 per visit",
      "details": "Includes performance tuning and adjustments.",
      "paymentLink": "#stripe"
    },
    "payments": {
      "description": "Secure checkout powered by Stripe. Apple Pay, Google Pay, and major cards supported."
    }
  },
  "supportPlans": {
    "basic": {
      "title": "Basic",
      "price": "$25/month",
      "features": [
        "Email support",
        "Seasonal tuning"
      ],
      "subscribeLink": "#stripe"
    },
    "premium": {
      "title": "Premium",
      "price": "$49/month",
      "features": [
        "Priority support",
        "Remote diagnostics",
        "Yearly on‑site visit"
      ],
      "subscribeLink": "#stripe"
    },
    "pro": {
      "title": "Pro",
      "price": "$79/month",
      "features": [
        "Unlimited support",
        "Emergency response",
        "Optimization visits"
      ],
      "subscribeLink": "#stripe"
    }
  },
  "contact": {
    "notes": "Service areas vary. Contact us to confirm availability.",
    "actions": [
      "Consultation",
      "Installation",
      "Support",
      "Request Service"
    ]
  },
  "marketing": {
    "headline": "Automate Your Lawn the Right Way",
    "subheadline": "Professional setup. Reliable performance. Less work for you.",
    "cta": "Get Started"
  },
  "legal": {
    "copyright": "© 2026 Solutions In Motion. All rights reserved.",
    "description": "Robotic lawn mower consulting and support. Independent service provider."
  }
}
